wireguard_tools/__init__.py
wireguard_tools/__main__.py
wireguard_tools/cli.py
wireguard_tools/curve25519.py
wireguard_tools/py.typed
wireguard_tools/wireguard_config.py
wireguard_tools/wireguard_device.py
wireguard_tools/wireguard_key.py
wireguard_tools/wireguard_netlink.py
wireguard_tools/wireguard_uapi.py
wireguard_tools-0.5.2.dist-info/LICENSE
wireguard_tools-0.5.2.dist-info/LICENSES/0BSD.txt
wireguard_tools-0.5.2.dist-info/LICENSES/CC-PDDC.txt
wireguard_tools-0.5.2.dist-info/LICENSES/MIT.txt
wireguard_tools-0.5.2.dist-info/METADATA
wireguard_tools-0.5.2.dist-info/WHEEL
wireguard_tools-0.5.2.dist-info/entry_points.txt
wireguard_tools-0.5.2.dist-info/RECORD
