Metadata-Version: 2.3
Name: wireguard-tools
Version: 0.5.2
Summary: Pure python reimplementation of wireguard-tools
License: MIT
Author: Carnegie Mellon University
Author-email: satya+group@cs.cmu.edu
Requires-Python: >=3.7,<4.0
Classifier: Development Status :: 4 - Beta
Classifier: Environment :: Console
Classifier: Intended Audience :: Developers
Classifier: Intended Audience :: End Users/Desktop
Classifier: License :: OSI Approved :: MIT License
Classifier: Programming Language :: Python :: 3
Classifier: Programming Language :: Python :: 3.7
Classifier: Programming Language :: Python :: 3.8
Classifier: Programming Language :: Python :: 3.9
Classifier: Programming Language :: Python :: 3.10
Classifier: Programming Language :: Python :: 3.11
Classifier: Programming Language :: Python :: 3.12
Classifier: Programming Language :: Python :: 3.13
Classifier: Topic :: Software Development :: Libraries :: Python Modules
Requires-Dist: attrs (>=22.1.0)
Requires-Dist: pyroute2 (>=0.7.3,<0.8.0)
Requires-Dist: segno (>=1.5.2,<2.0.0)
Project-URL: Repository, https://github.com/cmusatyalab/wireguard-tools
